[
  {
    "year": 2025,
    "school_name": "中国计量大学",
    "major_name": "质量管理工程",
    "major_group": "",
    "min_score": 671,
    "min_rank": 3356,
    "person_count": 2,
    "batch": "本科批",
    "major_description": "",
    "subject_requirement": "必选物理",
    "province": "海南",
    "level": "普通本科",
    "nature": "公办"
  },
  {
    "year": 2025,
    "school_name": "中国计量大学",
    "major_name": "测控技术与仪器",
    "major_group": "",
    "min_score": 653,
    "min_rank": 4856,
    "person_count": 2,
    "batch": "本科批",
    "major_description": "",
    "subject_requirement": "物+化(2科必选)",
    "province": "海南",
    "level": "普通本科",
    "nature": "公办"
  },
  {
    "year": 2025,
    "school_name": "中国计量大学",
    "major_name": "光电信息科学与工程",
    "major_group": "",
    "min_score": 649,
    "min_rank": 5269,
    "person_count": 1,
    "batch": "本科批",
    "major_description": "",
    "subject_requirement": "物+化(2科必选)",
    "province": "海南",
    "level": "普通本科",
    "nature": "公办"
  },
  {
    "year": 2025,
    "school_name": "中国计量大学",
    "major_name": "电子信息工程",
    "major_group": "",
    "min_score": 648,
    "min_rank": 5356,
    "person_count": 2,
    "batch": "本科批",
    "major_description": "",
    "subject_requirement": "物+化(2科必选)",
    "province": "海南",
    "level": "普通本科",
    "nature": "公办"
  },
  {
    "year": 2025,
    "school_name": "中国计量大学",
    "major_name": "电气工程及其自动化",
    "major_group": "",
    "min_score": 648,
    "min_rank": 5356,
    "person_count": 2,
    "batch": "本科批",
    "major_description": "",
    "subject_requirement": "物+化(2科必选)",
    "province": "海南",
    "level": "普通本科",
    "nature": "公办"
  },
  {
    "year": 2025,
    "school_name": "中国计量大学",
    "major_name": "标准化工程",
    "major_group": "",
    "min_score": 645,
    "min_rank": 5663,
    "person_count": 2,
    "batch": "本科批",
    "major_description": "",
    "subject_requirement": "必选物理",
    "province": "海南",
    "level": "普通本科",
    "nature": "公办"
  },
  {
    "year": 2025,
    "school_name": "中国计量大学",
    "major_name": "通信工程",
    "major_group": "",
    "min_score": 645,
    "min_rank": 5663,
    "person_count": 2,
    "batch": "本科批",
    "major_description": "",
    "subject_requirement": "物+化(2科必选)",
    "province": "海南",
    "level": "普通本科",
    "nature": "公办"
  }
]