[
  {
    "year": 2024,
    "school_name": "兰州大学",
    "major_name": "汉语言文学",
    "major_group": "",
    "min_score": 710,
    "min_rank": 1375,
    "person_count": 2,
    "batch": "本科批",
    "major_description": "",
    "subject_requirement": "必选历史",
    "province": "海南",
    "level": "985",
    "nature": "公办"
  },
  {
    "year": 2024,
    "school_name": "兰州大学",
    "major_name": "法学",
    "major_group": "",
    "min_score": 700,
    "min_rank": 1737,
    "person_count": 2,
    "batch": "本科批",
    "major_description": "",
    "subject_requirement": "不限",
    "province": "海南",
    "level": "985",
    "nature": "公办"
  },
  {
    "year": 2024,
    "school_name": "兰州大学",
    "major_name": "计算机类",
    "major_group": "",
    "min_score": 693,
    "min_rank": 2052,
    "person_count": 3,
    "batch": "本科批",
    "major_description": "",
    "subject_requirement": "物+化(2科必选)",
    "province": "海南",
    "level": "985",
    "nature": "公办"
  },
  {
    "year": 2024,
    "school_name": "兰州大学",
    "major_name": "马克思主义理论类",
    "major_group": "",
    "min_score": 689,
    "min_rank": 2243,
    "person_count": 3,
    "batch": "本科批",
    "major_description": "",
    "subject_requirement": "必选政治",
    "province": "海南",
    "level": "985",
    "nature": "公办"
  },
  {
    "year": 2024,
    "school_name": "兰州大学",
    "major_name": "大气科学类",
    "major_group": "",
    "min_score": 684,
    "min_rank": 2517,
    "person_count": 3,
    "batch": "本科批",
    "major_description": "",
    "subject_requirement": "物+化(2科必选)",
    "province": "海南",
    "level": "985",
    "nature": "公办"
  },
  {
    "year": 2024,
    "school_name": "兰州大学",
    "major_name": "政治学类",
    "major_group": "",
    "min_score": 684,
    "min_rank": 2517,
    "person_count": 4,
    "batch": "本科批",
    "major_description": "",
    "subject_requirement": "必选政治",
    "province": "海南",
    "level": "985",
    "nature": "公办"
  },
  {
    "year": 2024,
    "school_name": "兰州大学",
    "major_name": "核工程与核技术",
    "major_group": "",
    "min_score": 684,
    "min_rank": 2517,
    "person_count": 3,
    "batch": "本科批",
    "major_description": "",
    "subject_requirement": "物+化(2科必选)",
    "province": "海南",
    "level": "985",
    "nature": "公办"
  }
]