[
  {
    "year": 2025,
    "school_name": "华北电力大学(保定)",
    "major_name": "电气工程及其自动化",
    "major_group": "",
    "min_score": 713,
    "min_rank": 1292,
    "person_count": 3,
    "batch": "本科批",
    "major_description": "",
    "subject_requirement": "物+化(2科必选)",
    "province": "海南",
    "level": "211",
    "nature": "公办"
  },
  {
    "year": 2025,
    "school_name": "华北电力大学(保定)",
    "major_name": "通信工程",
    "major_group": "",
    "min_score": 710,
    "min_rank": 1386,
    "person_count": 1,
    "batch": "本科批",
    "major_description": "",
    "subject_requirement": "物+化(2科必选)",
    "province": "海南",
    "level": "211",
    "nature": "公办"
  },
  {
    "year": 2025,
    "school_name": "华北电力大学(保定)",
    "major_name": "应用物理学",
    "major_group": "",
    "min_score": 685,
    "min_rank": 2483,
    "person_count": 1,
    "batch": "本科批",
    "major_description": "",
    "subject_requirement": "物+化(2科必选)",
    "province": "海南",
    "level": "211",
    "nature": "公办"
  },
  {
    "year": 2025,
    "school_name": "华北电力大学(保定)",
    "major_name": "氢能科学与工程",
    "major_group": "",
    "min_score": 685,
    "min_rank": 2483,
    "person_count": 1,
    "batch": "本科批",
    "major_description": "",
    "subject_requirement": "物+化(2科必选)",
    "province": "海南",
    "level": "211",
    "nature": "公办"
  },
  {
    "year": 2025,
    "school_name": "华北电力大学(保定)",
    "major_name": "储能科学与工程",
    "major_group": "",
    "min_score": 676,
    "min_rank": 3029,
    "person_count": 1,
    "batch": "本科批",
    "major_description": "",
    "subject_requirement": "物+化(2科必选)",
    "province": "海南",
    "level": "211",
    "nature": "公办"
  },
  {
    "year": 2025,
    "school_name": "华北电力大学(保定)",
    "major_name": "计算机科学与技术",
    "major_group": "",
    "min_score": 675,
    "min_rank": 3092,
    "person_count": 1,
    "batch": "本科批",
    "major_description": "",
    "subject_requirement": "物+化(2科必选)",
    "province": "海南",
    "level": "211",
    "nature": "公办"
  },
  {
    "year": 2025,
    "school_name": "华北电力大学(保定)",
    "major_name": "机械工程",
    "major_group": "",
    "min_score": 674,
    "min_rank": 3157,
    "person_count": 1,
    "batch": "本科批",
    "major_description": "",
    "subject_requirement": "物+化(2科必选)",
    "province": "海南",
    "level": "211",
    "nature": "公办"
  },
  {
    "year": 2025,
    "school_name": "华北电力大学(保定)",
    "major_name": "建筑环境与能源应用工程",
    "major_group": "",
    "min_score": 672,
    "min_rank": 3289,
    "person_count": 1,
    "batch": "本科批",
    "major_description": "",
    "subject_requirement": "物+化(2科必选)",
    "province": "海南",
    "level": "211",
    "nature": "公办"
  },
  {
    "year": 2025,
    "school_name": "华北电力大学(保定)",
    "major_name": "环境工程",
    "major_group": "",
    "min_score": 672,
    "min_rank": 3289,
    "person_count": 1,
    "batch": "本科批",
    "major_description": "",
    "subject_requirement": "物+化(2科必选)",
    "province": "海南",
    "level": "211",
    "nature": "公办"
  },
  {
    "year": 2025,
    "school_name": "华北电力大学(保定)",
    "major_name": "软件工程",
    "major_group": "",
    "min_score": 672,
    "min_rank": 3289,
    "person_count": 1,
    "batch": "本科批",
    "major_description": "",
    "subject_requirement": "物+化(2科必选)",
    "province": "海南",
    "level": "211",
    "nature": "公办"
  },
  {
    "year": 2025,
    "school_name": "华北电力大学(保定)",
    "major_name": "信息与计算科学",
    "major_group": "",
    "min_score": 671,
    "min_rank": 3356,
    "person_count": 1,
    "batch": "本科批",
    "major_description": "",
    "subject_requirement": "物+化(2科必选)",
    "province": "海南",
    "level": "211",
    "nature": "公办"
  },
  {
    "year": 2025,
    "school_name": "华北电力大学(保定)",
    "major_name": "智能科学与技术",
    "major_group": "",
    "min_score": 670,
    "min_rank": 3448,
    "person_count": 1,
    "batch": "本科批",
    "major_description": "",
    "subject_requirement": "必选物理",
    "province": "海南",
    "level": "211",
    "nature": "公办"
  },
  {
    "year": 2025,
    "school_name": "华北电力大学(保定)",
    "major_name": "工业工程",
    "major_group": "",
    "min_score": 654,
    "min_rank": 4768,
    "person_count": 1,
    "batch": "本科批",
    "major_description": "",
    "subject_requirement": "必选物理",
    "province": "海南",
    "level": "211",
    "nature": "公办"
  },
  {
    "year": 2025,
    "school_name": "华北电力大学(保定)",
    "major_name": "工程造价",
    "major_group": "",
    "min_score": 652,
    "min_rank": 4963,
    "person_count": 2,
    "batch": "本科批",
    "major_description": "",
    "subject_requirement": "必选物理",
    "province": "海南",
    "level": "211",
    "nature": "公办"
  }
]