[
  {
    "year": 2025,
    "school_name": "西南民族大学",
    "major_name": "汉语言文学",
    "major_group": "",
    "min_score": 639,
    "min_rank": 6349,
    "person_count": 3,
    "batch": "本科批",
    "major_description": "(师范)",
    "subject_requirement": "不限",
    "province": "海南",
    "level": "普通本科",
    "nature": "公办"
  },
  {
    "year": 2025,
    "school_name": "西南民族大学",
    "major_name": "法学",
    "major_group": "",
    "min_score": 620,
    "min_rank": 8822,
    "person_count": 3,
    "batch": "本科批",
    "major_description": "",
    "subject_requirement": "不限",
    "province": "海南",
    "level": "普通本科",
    "nature": "公办"
  },
  {
    "year": 2025,
    "school_name": "西南民族大学",
    "major_name": "历史学类",
    "major_group": "",
    "min_score": 613,
    "min_rank": 9938,
    "person_count": 3,
    "batch": "本科批",
    "major_description": "(包含专业:历史学、文物与博物馆学)",
    "subject_requirement": "不限",
    "province": "海南",
    "level": "普通本科",
    "nature": "公办"
  },
  {
    "year": 2025,
    "school_name": "西南民族大学",
    "major_name": "汉语言文学",
    "major_group": "",
    "min_score": 611,
    "min_rank": 10262,
    "person_count": 4,
    "batch": "本科批",
    "major_description": "",
    "subject_requirement": "不限",
    "province": "海南",
    "level": "普通本科",
    "nature": "公办"
  },
  {
    "year": 2025,
    "school_name": "西南民族大学",
    "major_name": "经济学",
    "major_group": "",
    "min_score": 604,
    "min_rank": 11462,
    "person_count": 3,
    "batch": "本科批",
    "major_description": "",
    "subject_requirement": "不限",
    "province": "海南",
    "level": "普通本科",
    "nature": "公办"
  },
  {
    "year": 2025,
    "school_name": "西南民族大学",
    "major_name": "哲学",
    "major_group": "",
    "min_score": 602,
    "min_rank": 11828,
    "person_count": 3,
    "batch": "本科批",
    "major_description": "",
    "subject_requirement": "不限",
    "province": "海南",
    "level": "普通本科",
    "nature": "公办"
  },
  {
    "year": 2025,
    "school_name": "西南民族大学",
    "major_name": "国际经济与贸易",
    "major_group": "",
    "min_score": 602,
    "min_rank": 11828,
    "person_count": 3,
    "batch": "本科批",
    "major_description": "",
    "subject_requirement": "不限",
    "province": "海南",
    "level": "普通本科",
    "nature": "公办"
  },
  {
    "year": 2025,
    "school_name": "西南民族大学",
    "major_name": "社会学类",
    "major_group": "",
    "min_score": 602,
    "min_rank": 11828,
    "person_count": 3,
    "batch": "本科批",
    "major_description": "(包含专业:社会学、社会工作)",
    "subject_requirement": "不限",
    "province": "海南",
    "level": "普通本科",
    "nature": "公办"
  },
  {
    "year": 2025,
    "school_name": "西南民族大学",
    "major_name": "行政管理",
    "major_group": "",
    "min_score": 602,
    "min_rank": 11828,
    "person_count": 3,
    "batch": "本科批",
    "major_description": "",
    "subject_requirement": "不限",
    "province": "海南",
    "level": "普通本科",
    "nature": "公办"
  },
  {
    "year": 2025,
    "school_name": "西南民族大学",
    "major_name": "应用心理学",
    "major_group": "",
    "min_score": 600,
    "min_rank": 12182,
    "person_count": 3,
    "batch": "本科批",
    "major_description": "",
    "subject_requirement": "不限",
    "province": "海南",
    "level": "普通本科",
    "nature": "公办"
  },
  {
    "year": 2025,
    "school_name": "西南民族大学",
    "major_name": "金融学",
    "major_group": "",
    "min_score": 600,
    "min_rank": 12182,
    "person_count": 3,
    "batch": "本科批",
    "major_description": "",
    "subject_requirement": "不限",
    "province": "海南",
    "level": "普通本科",
    "nature": "公办"
  },
  {
    "year": 2025,
    "school_name": "西南民族大学",
    "major_name": "旅游管理",
    "major_group": "",
    "min_score": 599,
    "min_rank": 12365,
    "person_count": 4,
    "batch": "本科批",
    "major_description": "",
    "subject_requirement": "不限",
    "province": "海南",
    "level": "普通本科",
    "nature": "公办"
  },
  {
    "year": 2025,
    "school_name": "西南民族大学",
    "major_name": "英语",
    "major_group": "",
    "min_score": 598,
    "min_rank": 12558,
    "person_count": 4,
    "batch": "本科批",
    "major_description": "",
    "subject_requirement": "不限",
    "province": "海南",
    "level": "普通本科",
    "nature": "公办"
  },
  {
    "year": 2025,
    "school_name": "西南民族大学",
    "major_name": "人力资源管理",
    "major_group": "",
    "min_score": 597,
    "min_rank": 12734,
    "person_count": 3,
    "batch": "本科批",
    "major_description": "",
    "subject_requirement": "不限",
    "province": "海南",
    "level": "普通本科",
    "nature": "公办"
  },
  {
    "year": 2025,
    "school_name": "西南民族大学",
    "major_name": "建筑学",
    "major_group": "",
    "min_score": 595,
    "min_rank": 13116,
    "person_count": 3,
    "batch": "本科批",
    "major_description": "",
    "subject_requirement": "不限",
    "province": "海南",
    "level": "普通本科",
    "nature": "公办"
  },
  {
    "year": 2025,
    "school_name": "西南民族大学",
    "major_name": "财务管理",
    "major_group": "",
    "min_score": 595,
    "min_rank": 13116,
    "person_count": 3,
    "batch": "本科批",
    "major_description": "",
    "subject_requirement": "不限",
    "province": "海南",
    "level": "普通本科",
    "nature": "公办"
  },
  {
    "year": 2025,
    "school_name": "西南民族大学",
    "major_name": "学前教育",
    "major_group": "",
    "min_score": 594,
    "min_rank": 13340,
    "person_count": 3,
    "batch": "本科批",
    "major_description": "(师范)",
    "subject_requirement": "不限",
    "province": "海南",
    "level": "普通本科",
    "nature": "公办"
  },
  {
    "year": 2025,
    "school_name": "西南民族大学",
    "major_name": "电气工程及其自动化",
    "major_group": "",
    "min_score": 593,
    "min_rank": 13518,
    "person_count": 4,
    "batch": "本科批",
    "major_description": "",
    "subject_requirement": "物+化(2科必选)",
    "province": "海南",
    "level": "普通本科",
    "nature": "公办"
  },
  {
    "year": 2025,
    "school_name": "西南民族大学",
    "major_name": "计算机科学与技术",
    "major_group": "",
    "min_score": 591,
    "min_rank": 13911,
    "person_count": 4,
    "batch": "本科批",
    "major_description": "",
    "subject_requirement": "物+化(2科必选)",
    "province": "海南",
    "level": "普通本科",
    "nature": "公办"
  },
  {
    "year": 2025,
    "school_name": "西南民族大学",
    "major_name": "中国少数民族语言文学",
    "major_group": "",
    "min_score": 581,
    "min_rank": 16028,
    "person_count": 2,
    "batch": "本科批",
    "major_description": "(藏语言零起点班)(藏语言零起点班;学生入校后不得转入其他专业学习;只招收填报该志愿考生;录取过程中不调剂录取)",
    "subject_requirement": "不限",
    "province": "海南",
    "level": "普通本科",
    "nature": "公办"
  },
  {
    "year": 2025,
    "school_name": "西南民族大学",
    "major_name": "动物医学",
    "major_group": "",
    "min_score": 578,
    "min_rank": 16685,
    "person_count": 5,
    "batch": "本科批",
    "major_description": "",
    "subject_requirement": "物+化(2科必选)",
    "province": "海南",
    "level": "普通本科",
    "nature": "公办"
  },
  {
    "year": 2025,
    "school_name": "西南民族大学",
    "major_name": "中国少数民族语言文学",
    "major_group": "",
    "min_score": 573,
    "min_rank": 17772,
    "person_count": 2,
    "batch": "本科批",
    "major_description": "(彝语言零起点班)(彝语言零起点班;学生入校后不得转入其他专业学习;只招收填报该志愿考生;录取过程中不调剂录取)",
    "subject_requirement": "物+化(2科必选)",
    "province": "海南",
    "level": "普通本科",
    "nature": "公办"
  },
  {
    "year": 2025,
    "school_name": "西南民族大学",
    "major_name": "软件工程",
    "major_group": "",
    "min_score": 567,
    "min_rank": 19243,
    "person_count": 4,
    "batch": "本科批",
    "major_description": "",
    "subject_requirement": "物+化(2科必选)",
    "province": "海南",
    "level": "普通本科",
    "nature": "公办"
  },
  {
    "year": 2025,
    "school_name": "西南民族大学",
    "major_name": "通信工程",
    "major_group": "",
    "min_score": 565,
    "min_rank": 19738,
    "person_count": 6,
    "batch": "本科批",
    "major_description": "",
    "subject_requirement": "物+化(2科必选)",
    "province": "海南",
    "level": "普通本科",
    "nature": "公办"
  },
  {
    "year": 2025,
    "school_name": "西南民族大学",
    "major_name": "电子信息工程",
    "major_group": "",
    "min_score": 564,
    "min_rank": 19954,
    "person_count": 5,
    "batch": "本科批",
    "major_description": "",
    "subject_requirement": "物+化(2科必选)",
    "province": "海南",
    "level": "普通本科",
    "nature": "公办"
  },
  {
    "year": 2025,
    "school_name": "西南民族大学",
    "major_name": "中药学",
    "major_group": "",
    "min_score": 562,
    "min_rank": 20421,
    "person_count": 4,
    "batch": "本科批",
    "major_description": "",
    "subject_requirement": "物+化(2科必选)",
    "province": "海南",
    "level": "普通本科",
    "nature": "公办"
  },
  {
    "year": 2025,
    "school_name": "西南民族大学",
    "major_name": "网络工程",
    "major_group": "",
    "min_score": 562,
    "min_rank": 20421,
    "person_count": 4,
    "batch": "本科批",
    "major_description": "",
    "subject_requirement": "物+化(2科必选)",
    "province": "海南",
    "level": "普通本科",
    "nature": "公办"
  },
  {
    "year": 2025,
    "school_name": "西南民族大学",
    "major_name": "食品科学与工程类",
    "major_group": "",
    "min_score": 562,
    "min_rank": 20421,
    "person_count": 5,
    "batch": "本科批",
    "major_description": "(包含专业:食品科学与工程、食品质量与安全)",
    "subject_requirement": "物+化(2科必选)",
    "province": "海南",
    "level": "普通本科",
    "nature": "公办"
  },
  {
    "year": 2025,
    "school_name": "西南民族大学",
    "major_name": "动物科学",
    "major_group": "",
    "min_score": 559,
    "min_rank": 21189,
    "person_count": 4,
    "batch": "本科批",
    "major_description": "",
    "subject_requirement": "物+化(2科必选)",
    "province": "海南",
    "level": "普通本科",
    "nature": "公办"
  },
  {
    "year": 2025,
    "school_name": "西南民族大学",
    "major_name": "化学工程与工艺",
    "major_group": "",
    "min_score": 559,
    "min_rank": 21189,
    "person_count": 3,
    "batch": "本科批",
    "major_description": "",
    "subject_requirement": "物+化(2科必选)",
    "province": "海南",
    "level": "普通本科",
    "nature": "公办"
  },
  {
    "year": 2025,
    "school_name": "西南民族大学",
    "major_name": "环境工程",
    "major_group": "",
    "min_score": 559,
    "min_rank": 21189,
    "person_count": 3,
    "batch": "本科批",
    "major_description": "",
    "subject_requirement": "物+化(2科必选)",
    "province": "海南",
    "level": "普通本科",
    "nature": "公办"
  },
  {
    "year": 2025,
    "school_name": "西南民族大学",
    "major_name": "生物技术",
    "major_group": "",
    "min_score": 559,
    "min_rank": 21189,
    "person_count": 5,
    "batch": "本科批",
    "major_description": "",
    "subject_requirement": "物+化(2科必选)",
    "province": "海南",
    "level": "普通本科",
    "nature": "公办"
  },
  {
    "year": 2025,
    "school_name": "西南民族大学",
    "major_name": "药学",
    "major_group": "",
    "min_score": 559,
    "min_rank": 21189,
    "person_count": 5,
    "batch": "本科批",
    "major_description": "",
    "subject_requirement": "物+化(2科必选)",
    "province": "海南",
    "level": "普通本科",
    "nature": "公办"
  }
]