[
  {
    "year": 2024,
    "school_name": "西北民族大学",
    "major_name": "法学",
    "major_group": "",
    "min_score": 607,
    "min_rank": 10761,
    "person_count": 2,
    "batch": "本科批",
    "major_description": "",
    "subject_requirement": "必选政治",
    "province": "海南",
    "level": "普通本科",
    "nature": "公办"
  },
  {
    "year": 2024,
    "school_name": "西北民族大学",
    "major_name": "汉语言文学",
    "major_group": "",
    "min_score": 596,
    "min_rank": 12722,
    "person_count": 3,
    "batch": "本科批",
    "major_description": "",
    "subject_requirement": "必选历史",
    "province": "海南",
    "level": "普通本科",
    "nature": "公办"
  },
  {
    "year": 2024,
    "school_name": "西北民族大学",
    "major_name": "国际经济与贸易",
    "major_group": "",
    "min_score": 582,
    "min_rank": 15570,
    "person_count": 2,
    "batch": "本科批",
    "major_description": "",
    "subject_requirement": "不限",
    "province": "海南",
    "level": "普通本科",
    "nature": "公办"
  },
  {
    "year": 2024,
    "school_name": "西北民族大学",
    "major_name": "旅游管理",
    "major_group": "",
    "min_score": 579,
    "min_rank": 16225,
    "person_count": 2,
    "batch": "本科批",
    "major_description": "",
    "subject_requirement": "不限",
    "province": "海南",
    "level": "普通本科",
    "nature": "公办"
  },
  {
    "year": 2024,
    "school_name": "西北民族大学",
    "major_name": "公共事业管理",
    "major_group": "",
    "min_score": 578,
    "min_rank": 16442,
    "person_count": 2,
    "batch": "本科批",
    "major_description": "",
    "subject_requirement": "不限",
    "province": "海南",
    "level": "普通本科",
    "nature": "公办"
  },
  {
    "year": 2024,
    "school_name": "西北民族大学",
    "major_name": "新闻传播学类",
    "major_group": "",
    "min_score": 576,
    "min_rank": 16888,
    "person_count": 8,
    "batch": "本科批",
    "major_description": "",
    "subject_requirement": "不限",
    "province": "海南",
    "level": "普通本科",
    "nature": "公办"
  },
  {
    "year": 2024,
    "school_name": "西北民族大学",
    "major_name": "护理学",
    "major_group": "",
    "min_score": 575,
    "min_rank": 17087,
    "person_count": 2,
    "batch": "本科批",
    "major_description": "",
    "subject_requirement": "必选化学",
    "province": "海南",
    "level": "普通本科",
    "nature": "公办"
  },
  {
    "year": 2024,
    "school_name": "西北民族大学",
    "major_name": "教育技术学",
    "major_group": "",
    "min_score": 574,
    "min_rank": 17335,
    "person_count": 2,
    "batch": "本科批",
    "major_description": "",
    "subject_requirement": "必选物理",
    "province": "海南",
    "level": "普通本科",
    "nature": "公办"
  },
  {
    "year": 2024,
    "school_name": "西北民族大学",
    "major_name": "动物医学",
    "major_group": "",
    "min_score": 566,
    "min_rank": 19137,
    "person_count": 1,
    "batch": "本科批",
    "major_description": "",
    "subject_requirement": "物+化(2科必选)",
    "province": "海南",
    "level": "普通本科",
    "nature": "公办"
  },
  {
    "year": 2024,
    "school_name": "西北民族大学",
    "major_name": "财务管理",
    "major_group": "",
    "min_score": 566,
    "min_rank": 19137,
    "person_count": 2,
    "batch": "本科批",
    "major_description": "",
    "subject_requirement": "不限",
    "province": "海南",
    "level": "普通本科",
    "nature": "公办"
  },
  {
    "year": 2024,
    "school_name": "西北民族大学",
    "major_name": "英语",
    "major_group": "",
    "min_score": 563,
    "min_rank": 19861,
    "person_count": 5,
    "batch": "本科批",
    "major_description": "",
    "subject_requirement": "不限",
    "province": "海南",
    "level": "普通本科",
    "nature": "公办"
  },
  {
    "year": 2024,
    "school_name": "西北民族大学",
    "major_name": "金融学",
    "major_group": "",
    "min_score": 556,
    "min_rank": 21627,
    "person_count": 2,
    "batch": "本科批",
    "major_description": "",
    "subject_requirement": "不限",
    "province": "海南",
    "level": "普通本科",
    "nature": "公办"
  },
  {
    "year": 2024,
    "school_name": "西北民族大学",
    "major_name": "土木工程",
    "major_group": "",
    "min_score": 555,
    "min_rank": 21888,
    "person_count": 1,
    "batch": "本科批",
    "major_description": "",
    "subject_requirement": "物+化(2科必选)",
    "province": "海南",
    "level": "普通本科",
    "nature": "公办"
  },
  {
    "year": 2024,
    "school_name": "西北民族大学",
    "major_name": "食品科学与工程",
    "major_group": "",
    "min_score": 554,
    "min_rank": 22142,
    "person_count": 1,
    "batch": "本科批",
    "major_description": "",
    "subject_requirement": "物+化(2科必选)",
    "province": "海南",
    "level": "普通本科",
    "nature": "公办"
  },
  {
    "year": 2024,
    "school_name": "西北民族大学",
    "major_name": "电气工程及其自动化",
    "major_group": "",
    "min_score": 536,
    "min_rank": 26922,
    "person_count": 3,
    "batch": "本科批",
    "major_description": "",
    "subject_requirement": "物+化(2科必选)",
    "province": "海南",
    "level": "普通本科",
    "nature": "公办"
  },
  {
    "year": 2024,
    "school_name": "西北民族大学",
    "major_name": "计算机类",
    "major_group": "",
    "min_score": 527,
    "min_rank": 29380,
    "person_count": 8,
    "batch": "本科批",
    "major_description": "",
    "subject_requirement": "物+化(2科必选)",
    "province": "海南",
    "level": "普通本科",
    "nature": "公办"
  },
  {
    "year": 2024,
    "school_name": "西北民族大学",
    "major_name": "电子信息类",
    "major_group": "",
    "min_score": 512,
    "min_rank": 33659,
    "person_count": 5,
    "batch": "本科批",
    "major_description": "",
    "subject_requirement": "物+化(2科必选)",
    "province": "海南",
    "level": "普通本科",
    "nature": "公办"
  }
]