[
  {
    "year": 2023,
    "school_name": "贺州学院",
    "major_name": "机械设计制造及其自动化",
    "major_group": "",
    "min_score": 553,
    "min_rank": 21291,
    "person_count": 4,
    "batch": "本科批",
    "major_description": "",
    "subject_requirement": "专业组（02） - 必选物理",
    "province": "海南",
    "level": "普通本科",
    "nature": "公办"
  },
  {
    "year": 2023,
    "school_name": "贺州学院",
    "major_name": "网络工程",
    "major_group": "",
    "min_score": 551,
    "min_rank": 21824,
    "person_count": 3,
    "batch": "本科批",
    "major_description": "",
    "subject_requirement": "专业组（02） - 必选物理",
    "province": "海南",
    "level": "普通本科",
    "nature": "公办"
  },
  {
    "year": 2023,
    "school_name": "贺州学院",
    "major_name": "工程造价",
    "major_group": "",
    "min_score": 549,
    "min_rank": 22315,
    "person_count": 3,
    "batch": "本科批",
    "major_description": "",
    "subject_requirement": "专业组（02） - 必选物理",
    "province": "海南",
    "level": "普通本科",
    "nature": "公办"
  },
  {
    "year": 2023,
    "school_name": "贺州学院",
    "major_name": "机器人工程",
    "major_group": "",
    "min_score": 549,
    "min_rank": 22315,
    "person_count": 3,
    "batch": "本科批",
    "major_description": "",
    "subject_requirement": "专业组（02） - 必选物理",
    "province": "海南",
    "level": "普通本科",
    "nature": "公办"
  }
]