[
  {
    "year": 2025,
    "school_name": "吉林建筑大学",
    "major_name": "建筑学",
    "major_group": "",
    "min_score": 517,
    "min_rank": 35222,
    "person_count": 2,
    "batch": "本科批",
    "major_description": "(要求有绘画基础；吉林建筑大学净月校区)",
    "subject_requirement": "不限",
    "province": "天津",
    "level": "普通本科",
    "nature": "公办"
  },
  {
    "year": 2025,
    "school_name": "吉林建筑大学",
    "major_name": "机械工程",
    "major_group": "",
    "min_score": 516,
    "min_rank": 35525,
    "person_count": 2,
    "batch": "本科批",
    "major_description": "(吉林建筑大学净月校区)",
    "subject_requirement": "物+化(2科必选)",
    "province": "天津",
    "level": "普通本科",
    "nature": "公办"
  },
  {
    "year": 2025,
    "school_name": "吉林建筑大学",
    "major_name": "网络工程",
    "major_group": "",
    "min_score": 516,
    "min_rank": 35525,
    "person_count": 4,
    "batch": "本科批",
    "major_description": "(吉林建筑大学净月校区)",
    "subject_requirement": "物+化(2科必选)",
    "province": "天津",
    "level": "普通本科",
    "nature": "公办"
  },
  {
    "year": 2025,
    "school_name": "吉林建筑大学",
    "major_name": "材料化学",
    "major_group": "",
    "min_score": 515,
    "min_rank": 35839,
    "person_count": 2,
    "batch": "本科批",
    "major_description": "(吉林建筑大学净月校区)",
    "subject_requirement": "物+化(2科必选)",
    "province": "天津",
    "level": "普通本科",
    "nature": "公办"
  },
  {
    "year": 2025,
    "school_name": "吉林建筑大学",
    "major_name": "遥感科学与技术",
    "major_group": "",
    "min_score": 515,
    "min_rank": 35839,
    "person_count": 2,
    "batch": "本科批",
    "major_description": "(吉林建筑大学净月校区)",
    "subject_requirement": "物+化(2科必选)",
    "province": "天津",
    "level": "普通本科",
    "nature": "公办"
  },
  {
    "year": 2025,
    "school_name": "吉林建筑大学",
    "major_name": "交通工程",
    "major_group": "",
    "min_score": 514,
    "min_rank": 36107,
    "person_count": 2,
    "batch": "本科批",
    "major_description": "(吉林建筑大学净月校区)",
    "subject_requirement": "物+化(2科必选)",
    "province": "天津",
    "level": "普通本科",
    "nature": "公办"
  },
  {
    "year": 2025,
    "school_name": "吉林建筑大学",
    "major_name": "工程管理",
    "major_group": "",
    "min_score": 514,
    "min_rank": 36107,
    "person_count": 2,
    "batch": "本科批",
    "major_description": "(吉林建筑大学净月校区)",
    "subject_requirement": "必选物理",
    "province": "天津",
    "level": "普通本科",
    "nature": "公办"
  },
  {
    "year": 2025,
    "school_name": "吉林建筑大学",
    "major_name": "经济统计学",
    "major_group": "",
    "min_score": 514,
    "min_rank": 36107,
    "person_count": 2,
    "batch": "本科批",
    "major_description": "(吉林建筑大学净月校区)",
    "subject_requirement": "必选物理",
    "province": "天津",
    "level": "普通本科",
    "nature": "公办"
  },
  {
    "year": 2025,
    "school_name": "吉林建筑大学",
    "major_name": "土木工程",
    "major_group": "",
    "min_score": 513,
    "min_rank": 36409,
    "person_count": 2,
    "batch": "本科批",
    "major_description": "(吉林建筑大学净月校区)",
    "subject_requirement": "物+化(2科必选)",
    "province": "天津",
    "level": "普通本科",
    "nature": "公办"
  },
  {
    "year": 2025,
    "school_name": "吉林建筑大学",
    "major_name": "地理信息科学",
    "major_group": "",
    "min_score": 513,
    "min_rank": 36409,
    "person_count": 2,
    "batch": "本科批",
    "major_description": "(吉林建筑大学净月校区)",
    "subject_requirement": "物+化(2科必选)",
    "province": "天津",
    "level": "普通本科",
    "nature": "公办"
  },
  {
    "year": 2025,
    "school_name": "吉林建筑大学",
    "major_name": "安全工程",
    "major_group": "",
    "min_score": 513,
    "min_rank": 36409,
    "person_count": 2,
    "batch": "本科批",
    "major_description": "(吉林建筑大学净月校区)",
    "subject_requirement": "物+化(2科必选)",
    "province": "天津",
    "level": "普通本科",
    "nature": "公办"
  },
  {
    "year": 2025,
    "school_name": "吉林建筑大学",
    "major_name": "测绘工程",
    "major_group": "",
    "min_score": 513,
    "min_rank": 36409,
    "person_count": 2,
    "batch": "本科批",
    "major_description": "(吉林建筑大学净月校区)",
    "subject_requirement": "物+化(2科必选)",
    "province": "天津",
    "level": "普通本科",
    "nature": "公办"
  },
  {
    "year": 2025,
    "school_name": "吉林建筑大学",
    "major_name": "给排水科学与工程",
    "major_group": "",
    "min_score": 513,
    "min_rank": 36409,
    "person_count": 2,
    "batch": "本科批",
    "major_description": "(吉林建筑大学净月校区)",
    "subject_requirement": "物+化(2科必选)",
    "province": "天津",
    "level": "普通本科",
    "nature": "公办"
  },
  {
    "year": 2025,
    "school_name": "吉林建筑大学",
    "major_name": "道路桥梁与渡河工程",
    "major_group": "",
    "min_score": 513,
    "min_rank": 36409,
    "person_count": 2,
    "batch": "本科批",
    "major_description": "(吉林建筑大学净月校区)",
    "subject_requirement": "物+化(2科必选)",
    "province": "天津",
    "level": "普通本科",
    "nature": "公办"
  },
  {
    "year": 2025,
    "school_name": "吉林建筑大学",
    "major_name": "工程管理",
    "major_group": "",
    "min_score": 507,
    "min_rank": 38187,
    "person_count": 2,
    "batch": "本科批",
    "major_description": "(中外合作办学)(与俄罗斯太平洋国立大学合作办学，录取有专业志愿的考生；吉林建筑大学净月校区)",
    "subject_requirement": "必选物理",
    "province": "天津",
    "level": "普通本科",
    "nature": "公办"
  },
  {
    "year": 2025,
    "school_name": "吉林建筑大学",
    "major_name": "土木工程",
    "major_group": "",
    "min_score": 501,
    "min_rank": 39953,
    "person_count": 4,
    "batch": "本科批",
    "major_description": "(中外合作办学)(与美国波特兰州立大学合作办学，录取有专业志愿的考生，宜英语考生填报；吉林建筑大学净月校区)",
    "subject_requirement": "物+化(2科必选)",
    "province": "天津",
    "level": "普通本科",
    "nature": "公办"
  }
]