[
  {
    "year": 2025,
    "school_name": "长春理工大学",
    "major_name": "光电信息科学与工程",
    "major_group": "",
    "min_score": 626,
    "min_rank": 7354,
    "person_count": 2,
    "batch": "本科批",
    "major_description": "(工学方向，授工学学位；长春理工大学卫星路校区[主校区])",
    "subject_requirement": "物+化(2科必选)",
    "province": "天津",
    "level": "普通本科",
    "nature": "公办"
  },
  {
    "year": 2025,
    "school_name": "长春理工大学",
    "major_name": "测控技术与仪器",
    "major_group": "",
    "min_score": 614,
    "min_rank": 9791,
    "person_count": 3,
    "batch": "本科批",
    "major_description": "(长春理工大学卫星路校区[主校区])",
    "subject_requirement": "物+化(2科必选)",
    "province": "天津",
    "level": "普通本科",
    "nature": "公办"
  },
  {
    "year": 2025,
    "school_name": "长春理工大学",
    "major_name": "光电信息科学与工程",
    "major_group": "",
    "min_score": 611,
    "min_rank": 10462,
    "person_count": 1,
    "batch": "本科批",
    "major_description": "(中外合作办学)(与英国西苏格兰大学合作办学，授工学学位；外方授课教师采用全英文授课，非英语语种考生不宜报考；学费暂定28000元，实际按批复文件收取；长春理工大学卫星路校区[主校区])",
    "subject_requirement": "物+化(2科必选)",
    "province": "天津",
    "level": "普通本科",
    "nature": "公办"
  },
  {
    "year": 2025,
    "school_name": "长春理工大学",
    "major_name": "通信工程",
    "major_group": "",
    "min_score": 610,
    "min_rank": 10681,
    "person_count": 2,
    "batch": "本科批",
    "major_description": "(长春理工大学卫星路校区[主校区])",
    "subject_requirement": "物+化(2科必选)",
    "province": "天津",
    "level": "普通本科",
    "nature": "公办"
  },
  {
    "year": 2025,
    "school_name": "长春理工大学",
    "major_name": "光电信息科学与工程",
    "major_group": "",
    "min_score": 606,
    "min_rank": 11588,
    "person_count": 2,
    "batch": "本科批",
    "major_description": "(中外合作办学)(与美国特拉华州立大学合作办学，授理学学位；专业采用全英文授课，非英语语种考生不宜报考；学费暂定28000元，实际按批复文件收取；长春理工大学卫星路校区[主校区])",
    "subject_requirement": "物+化(2科必选)",
    "province": "天津",
    "level": "普通本科",
    "nature": "公办"
  },
  {
    "year": 2025,
    "school_name": "长春理工大学",
    "major_name": "电子信息工程",
    "major_group": "",
    "min_score": 602,
    "min_rank": 12510,
    "person_count": 3,
    "batch": "本科批",
    "major_description": "(长春理工大学卫星路校区[主校区])",
    "subject_requirement": "物+化(2科必选)",
    "province": "天津",
    "level": "普通本科",
    "nature": "公办"
  },
  {
    "year": 2025,
    "school_name": "长春理工大学",
    "major_name": "化学工程与工艺",
    "major_group": "",
    "min_score": 601,
    "min_rank": 12738,
    "person_count": 1,
    "batch": "本科批",
    "major_description": "(长春理工大学卫星路校区[主校区])",
    "subject_requirement": "物+化(2科必选)",
    "province": "天津",
    "level": "普通本科",
    "nature": "公办"
  },
  {
    "year": 2025,
    "school_name": "长春理工大学",
    "major_name": "机械设计制造及其自动化",
    "major_group": "",
    "min_score": 600,
    "min_rank": 12965,
    "person_count": 2,
    "batch": "本科批",
    "major_description": "(长春理工大学卫星路校区[主校区])",
    "subject_requirement": "物+化(2科必选)",
    "province": "天津",
    "level": "普通本科",
    "nature": "公办"
  },
  {
    "year": 2025,
    "school_name": "长春理工大学",
    "major_name": "电气工程及其自动化",
    "major_group": "",
    "min_score": 600,
    "min_rank": 12965,
    "person_count": 2,
    "batch": "本科批",
    "major_description": "(长春理工大学卫星路校区[主校区])",
    "subject_requirement": "物+化(2科必选)",
    "province": "天津",
    "level": "普通本科",
    "nature": "公办"
  },
  {
    "year": 2025,
    "school_name": "长春理工大学",
    "major_name": "软件工程",
    "major_group": "",
    "min_score": 598,
    "min_rank": 13411,
    "person_count": 2,
    "batch": "本科批",
    "major_description": "(因教学特点和要求，非英语语种考生慎重报考；长春理工大学卫星路校区[主校区])",
    "subject_requirement": "物+化(2科必选)",
    "province": "天津",
    "level": "普通本科",
    "nature": "公办"
  },
  {
    "year": 2025,
    "school_name": "长春理工大学",
    "major_name": "机器人工程",
    "major_group": "",
    "min_score": 597,
    "min_rank": 13657,
    "person_count": 2,
    "batch": "本科批",
    "major_description": "(因教学特点和要求，非英语语种考生慎重报考；长春理工大学卫星路校区[主校区])",
    "subject_requirement": "物+化(2科必选)",
    "province": "天津",
    "level": "普通本科",
    "nature": "公办"
  },
  {
    "year": 2025,
    "school_name": "长春理工大学",
    "major_name": "光电信息科学与工程",
    "major_group": "",
    "min_score": 594,
    "min_rank": 14378,
    "person_count": 3,
    "batch": "本科批",
    "major_description": "(理学方向，授理学学位；长春理工大学卫星路校区[主校区])",
    "subject_requirement": "物+化(2科必选)",
    "province": "天津",
    "level": "普通本科",
    "nature": "公办"
  },
  {
    "year": 2025,
    "school_name": "长春理工大学",
    "major_name": "生物医学工程",
    "major_group": "",
    "min_score": 593,
    "min_rank": 14616,
    "person_count": 2,
    "batch": "本科批",
    "major_description": "(长春理工大学卫星路校区[主校区])",
    "subject_requirement": "物+化(2科必选)",
    "province": "天津",
    "level": "普通本科",
    "nature": "公办"
  },
  {
    "year": 2025,
    "school_name": "长春理工大学",
    "major_name": "生物工程",
    "major_group": "",
    "min_score": 588,
    "min_rank": 15802,
    "person_count": 2,
    "batch": "本科批",
    "major_description": "(长春理工大学卫星路校区[主校区])",
    "subject_requirement": "物+化(2科必选)",
    "province": "天津",
    "level": "普通本科",
    "nature": "公办"
  },
  {
    "year": 2025,
    "school_name": "长春理工大学",
    "major_name": "信息安全",
    "major_group": "",
    "min_score": 586,
    "min_rank": 16306,
    "person_count": 2,
    "batch": "本科批",
    "major_description": "(因教学特点和要求，非英语语种考生慎重报考；长春理工大学卫星路校区[主校区])",
    "subject_requirement": "物+化(2科必选)",
    "province": "天津",
    "level": "普通本科",
    "nature": "公办"
  },
  {
    "year": 2025,
    "school_name": "长春理工大学",
    "major_name": "功能材料",
    "major_group": "",
    "min_score": 582,
    "min_rank": 17292,
    "person_count": 4,
    "batch": "本科批",
    "major_description": "(长春理工大学卫星路校区[主校区])",
    "subject_requirement": "物+化(2科必选)",
    "province": "天津",
    "level": "普通本科",
    "nature": "公办"
  },
  {
    "year": 2025,
    "school_name": "长春理工大学",
    "major_name": "环境工程",
    "major_group": "",
    "min_score": 582,
    "min_rank": 17292,
    "person_count": 2,
    "batch": "本科批",
    "major_description": "(长春理工大学卫星路校区[主校区])",
    "subject_requirement": "物+化(2科必选)",
    "province": "天津",
    "level": "普通本科",
    "nature": "公办"
  },
  {
    "year": 2025,
    "school_name": "长春理工大学",
    "major_name": "数据科学与大数据技术",
    "major_group": "",
    "min_score": 581,
    "min_rank": 17539,
    "person_count": 3,
    "batch": "本科批",
    "major_description": "(因教学特点和要求，非英语语种考生慎重报考；长春理工大学卫星路校区[主校区])",
    "subject_requirement": "物+化(2科必选)",
    "province": "天津",
    "level": "普通本科",
    "nature": "公办"
  },
  {
    "year": 2025,
    "school_name": "长春理工大学",
    "major_name": "应用物理学",
    "major_group": "",
    "min_score": 580,
    "min_rank": 17773,
    "person_count": 3,
    "batch": "本科批",
    "major_description": "(长春理工大学卫星路校区[主校区])",
    "subject_requirement": "物+化(2科必选)",
    "province": "天津",
    "level": "普通本科",
    "nature": "公办"
  },
  {
    "year": 2025,
    "school_name": "长春理工大学",
    "major_name": "数学类",
    "major_group": "",
    "min_score": 579,
    "min_rank": 18022,
    "person_count": 4,
    "batch": "本科批",
    "major_description": "(数学与应用数学、信息与计算科学；长春理工大学卫星路校区[主校区])",
    "subject_requirement": "物+化(2科必选)",
    "province": "天津",
    "level": "普通本科",
    "nature": "公办"
  },
  {
    "year": 2025,
    "school_name": "长春理工大学",
    "major_name": "信息管理与信息系统",
    "major_group": "",
    "min_score": 574,
    "min_rank": 19332,
    "person_count": 3,
    "batch": "本科批",
    "major_description": "(因教学特点和要求，非英语语种考生慎重报考；长春理工大学卫星路校区[主校区])",
    "subject_requirement": "必选物理",
    "province": "天津",
    "level": "普通本科",
    "nature": "公办"
  },
  {
    "year": 2025,
    "school_name": "长春理工大学",
    "major_name": "工商管理类",
    "major_group": "",
    "min_score": 544,
    "min_rank": 27532,
    "person_count": 5,
    "batch": "本科批",
    "major_description": "(长春理工大学卫星路校区[主校区])",
    "subject_requirement": "不限",
    "province": "天津",
    "level": "普通本科",
    "nature": "公办"
  }
]