[
  {
    "year": 2025,
    "school_name": "青岛科技大学",
    "major_name": "法学",
    "major_group": "",
    "min_score": 594,
    "min_rank": 14378,
    "person_count": 2,
    "batch": "本科批",
    "major_description": "(崂山校区)",
    "subject_requirement": "不限",
    "province": "天津",
    "level": "普通本科",
    "nature": "公办"
  },
  {
    "year": 2025,
    "school_name": "青岛科技大学",
    "major_name": "电气工程及其自动化",
    "major_group": "",
    "min_score": 580,
    "min_rank": 17773,
    "person_count": 2,
    "batch": "本科批",
    "major_description": "(崂山校区)",
    "subject_requirement": "物+化(2科必选)",
    "province": "天津",
    "level": "普通本科",
    "nature": "公办"
  },
  {
    "year": 2025,
    "school_name": "青岛科技大学",
    "major_name": "化学工程与工艺",
    "major_group": "",
    "min_score": 567,
    "min_rank": 21240,
    "person_count": 2,
    "batch": "本科批",
    "major_description": "(不招收色盲、色弱；四方校区)",
    "subject_requirement": "物+化(2科必选)",
    "province": "天津",
    "level": "普通本科",
    "nature": "公办"
  },
  {
    "year": 2025,
    "school_name": "青岛科技大学",
    "major_name": "材料化学",
    "major_group": "",
    "min_score": 567,
    "min_rank": 21240,
    "person_count": 2,
    "batch": "本科批",
    "major_description": "(不招收色盲、色弱；四方校区)",
    "subject_requirement": "物+化(2科必选)",
    "province": "天津",
    "level": "普通本科",
    "nature": "公办"
  },
  {
    "year": 2025,
    "school_name": "青岛科技大学",
    "major_name": "应用物理学",
    "major_group": "",
    "min_score": 566,
    "min_rank": 21500,
    "person_count": 2,
    "batch": "本科批",
    "major_description": "(不招收色盲；崂山校区)",
    "subject_requirement": "物+化(2科必选)",
    "province": "天津",
    "level": "普通本科",
    "nature": "公办"
  },
  {
    "year": 2025,
    "school_name": "青岛科技大学",
    "major_name": "测控技术与仪器",
    "major_group": "",
    "min_score": 566,
    "min_rank": 21500,
    "person_count": 5,
    "batch": "本科批",
    "major_description": "(崂山校区)",
    "subject_requirement": "物+化(2科必选)",
    "province": "天津",
    "level": "普通本科",
    "nature": "公办"
  },
  {
    "year": 2025,
    "school_name": "青岛科技大学",
    "major_name": "高分子材料与工程",
    "major_group": "",
    "min_score": 566,
    "min_rank": 21500,
    "person_count": 5,
    "batch": "本科批",
    "major_description": "(崂山校区)",
    "subject_requirement": "物+化(2科必选)",
    "province": "天津",
    "level": "普通本科",
    "nature": "公办"
  },
  {
    "year": 2025,
    "school_name": "青岛科技大学",
    "major_name": "计算机科学与技术",
    "major_group": "",
    "min_score": 565,
    "min_rank": 21754,
    "person_count": 5,
    "batch": "本科批",
    "major_description": "(崂山校区)",
    "subject_requirement": "物+化(2科必选)",
    "province": "天津",
    "level": "普通本科",
    "nature": "公办"
  },
  {
    "year": 2025,
    "school_name": "青岛科技大学",
    "major_name": "过程装备与控制工程",
    "major_group": "",
    "min_score": 564,
    "min_rank": 22032,
    "person_count": 2,
    "batch": "本科批",
    "major_description": "(不招收色盲色弱；崂山校区)",
    "subject_requirement": "物+化(2科必选)",
    "province": "天津",
    "level": "普通本科",
    "nature": "公办"
  },
  {
    "year": 2025,
    "school_name": "青岛科技大学",
    "major_name": "智能制造工程",
    "major_group": "",
    "min_score": 563,
    "min_rank": 22282,
    "person_count": 2,
    "batch": "本科批",
    "major_description": "(崂山校区)",
    "subject_requirement": "物+化(2科必选)",
    "province": "天津",
    "level": "普通本科",
    "nature": "公办"
  },
  {
    "year": 2025,
    "school_name": "青岛科技大学",
    "major_name": "材料物理",
    "major_group": "",
    "min_score": 563,
    "min_rank": 22282,
    "person_count": 2,
    "batch": "本科批",
    "major_description": "(不招收色盲；四方校区)",
    "subject_requirement": "物+化(2科必选)",
    "province": "天津",
    "level": "普通本科",
    "nature": "公办"
  },
  {
    "year": 2025,
    "school_name": "青岛科技大学",
    "major_name": "制药工程",
    "major_group": "",
    "min_score": 562,
    "min_rank": 22547,
    "person_count": 4,
    "batch": "本科批",
    "major_description": "(不招收色盲、色弱；四方校区)",
    "subject_requirement": "物+化(2科必选)",
    "province": "天津",
    "level": "普通本科",
    "nature": "公办"
  },
  {
    "year": 2025,
    "school_name": "青岛科技大学",
    "major_name": "海洋科学",
    "major_group": "",
    "min_score": 562,
    "min_rank": 22547,
    "person_count": 4,
    "batch": "本科批",
    "major_description": "(不招收色盲、色弱；四方校区)",
    "subject_requirement": "物+化(2科必选)",
    "province": "天津",
    "level": "普通本科",
    "nature": "公办"
  },
  {
    "year": 2025,
    "school_name": "青岛科技大学",
    "major_name": "复合材料与工程",
    "major_group": "",
    "min_score": 561,
    "min_rank": 22809,
    "person_count": 3,
    "batch": "本科批",
    "major_description": "(四方校区)",
    "subject_requirement": "物+化(2科必选)",
    "province": "天津",
    "level": "普通本科",
    "nature": "公办"
  }
]